pydantic_gen/__init__.py
pydantic_gen/err.py
pydantic_gen/main.py
pydantic_gen/templates.yml
pydantic_gen-0.3.5.dist-info/WHEEL
pydantic_gen-0.3.5.dist-info/METADATA
pydantic_gen-0.3.5.dist-info/RECORD
