Metadata-Version: 2.1
Name: pydantic-gen
Version: 0.3.5
Summary: Code generator for pydantic schemas
Home-page: https://github.com/licht1stein/pydantic-gen
License: MIT
Author: MB
Author-email: mb@blaster.ai
Requires-Python: >=3.6,<4.0
Classifier: License :: OSI Approved :: MIT License
Classifier: Programming Language :: Python :: 3
Classifier: Programming Language :: Python :: 3.6
Classifier: Programming Language :: Python :: 3.7
Classifier: Programming Language :: Python :: 3.8
Requires-Dist: attrs (>=19.3.0,<20.0.0)
Requires-Dist: black (>=19.10b0,<20.0)
Requires-Dist: jinja2 (>=2.11.2,<3.0.0)
Requires-Dist: pydantic (>=1.4,<2.0)
Requires-Dist: python-box (>=4.2.2,<5.0.0)
Requires-Dist: ruamel.yaml (>=0.16.10,<0.17.0)
